{
  "mcpServers": {
    "auto_worklog": {
      "command": "node",
      "args": ["/home/apic/python/auto_worklog-mcp/dist/index.js"],
      "env": {
        "GIT_REPO_PATH": "/home/apic/python/worklog",
        "GIT_BRANCH": "Inyoung",
        "GIT_USER_NAME": "dlsdud9098",
        "GIT_USER_EMAIL": "dlsdud9098@naver.com",
        "GIT_ACCESS_TOKEN": "ghp_YOUR_TOKEN_HERE",
        "WORK_BRANCH": "main",
        "USE_DAILY_NOTE": "글리터 홈페이지,publishing.gltr-ous.us,text2cuts,프로젝트4,프로젝트5",
        "DEFAULT_PROJECT": "글리터 홈페이지",
        "AUTO_CREATE_PR": "true",
        "AUTO_MERGE_PR": "false",
        "PR_TARGET_BRANCH": "main",
        "PR_MERGE_METHOD": "merge"
      }
    }
  }
}